LICENSE
MANIFEST.in
README.rst
setup.py
django_auto_mutations/VERSION
django_auto_mutations/__init__.py
django_auto_mutations/auto_mutation.py
django_auto_mutations/settings.py
django_auto_mutations/urls.py
django_auto_mutations/wsgi.py
django_auto_mutations.egg-info/PKG-INFO
django_auto_mutations.egg-info/SOURCES.txt
django_auto_mutations.egg-info/dependency_links.txt
django_auto_mutations.egg-info/top_level.txt
docs/README.md